{
    "Hab": {
        "1": {
            "1": {
                "1": {
                    "hb": "המשׂא",
                    "gr": "τὸ λῆμμα"
                },
                "2": {
                    "hb": "אשׁר",
                    "gr": "ὃ"
                },
                "3": {
                    "hb": "חזה",
                    "gr": "εἶδεν"
                },
                "4": {
                    "hb": "חבקוק",
                    "gr": "αμβακουμ"
                },
                "5": {
                    "hb": "הנביא",
                    "gr": "ὁ προφήτης"
                }
            },
            "2": {
                "1": {
                    "hb": "עד",
                    "gr": "ἕως"
                },
                "2": {
                    "hb": "אנה",
                    "gr": "τίνος"
                },
                "3": {
                    "hb": "יהוה",
                    "gr": "κύριε"
                },
                "4": {
                    "hb": "שׁועתי",
                    "gr": "κεκράξομαι"
                },
                "5": {
                    "hb": "ולא",
                    "gr": "καὶ οὐ μὴ"
                },
                "6": {
                    "hb": "תשׁמע",
                    "gr": "εἰσακούσῃς"
                },
                "7": {
                    "hb": "אזעק",
                    "gr": "βοήσομαι"
                },
                "8": {
                    "hb": "אליך",
                    "gr": "πρὸς σὲ"
                },
                "9": {
                    "hb": "חמס",
                    "gr": "ἀδικούμενος"
                },
                "10": {
                    "hb": "ולא",
                    "gr": "καὶ οὐ"
                },
                "11": {
                    "hb": "תושׁיע",
                    "gr": "σώσεις"
                }
            },
            "3": {
                "1": {
                    "hb": "למה",
                    "gr": "ἵνα τί"
                },
                "2": {
                    "hb": "תראני",
                    "gr": "μοι ^ ἔδειξας"
                },
                "3": {
                    "hb": "און",
                    "gr": "κόπους"
                },
                "4": {
                    "hb": "ועמל",
                    "gr": "καὶ πόνους"
                },
                "5": {
                    "hb": "תביט",
                    "gr": "ἐπιβλέπειν"
                },
                "6": {
                    "hb": "ושׁד",
                    "gr": "ταλαιπωρίαν"
                },
                "7": {
                    "hb": "וחמס",
                    "gr": "καὶ ἀσέβειαν"
                },
                "8": {
                    "hb": "לנגדי",
                    "gr": "ἐξ ἐναντίας μου"
                },
                "9": {
                    "hb": "ויהי",
                    "gr": "γέγονεν"
                },
                "10": {
                    "hb": "ריב",
                    "gr": "κρίσις"
                },
                "11": {
                    "hb": "ומדון =?ומדין .wy",
                    "gr": "καὶ ὁ κριτὴς"
                },
                "12": {
                    "hb": "ישׂא",
                    "gr": "λαμβάνει"
                }
            },
            "4": {
                "1": {
                    "hb": "על כן",
                    "gr": "διὰ τοῦτο"
                },
                "2": {
                    "hb": "תפוג =@פרר",
                    "gr": "διεσκέδασται"
                },
                "3": {
                    "hb": "תורה",
                    "gr": "νόμος"
                },
                "4": {
                    "hb": "ולא",
                    "gr": "καὶ οὐ"
                },
                "5": {
                    "hb": "יצא",
                    "gr": "διεξάγεται"
                },
                "6": {
                    "hb": "לנצח",
                    "gr": "εἰς τέλος"
                },
                "7": {
                    "hb": "משׁפט",
                    "gr": "κρίμα"
                },
                "8": {
                    "hb": "כי",
                    "gr": "ὅτι"
                },
                "9": {
                    "hb": "רשׁע",
                    "gr": "ὁ ἀσεβὴς"
                },
                "10": {
                    "hb": "מכתיר",
                    "gr": "καταδυναστεύει"
                },
                "11": {
                    "hb": "את הצדיק",
                    "gr": "τὸν δίκαιον"
                },
                "12": {
                    "hb": "על כן",
                    "gr": "ἕνεκεν τούτου"
                },
                "13": {
                    "hb": "יצא",
                    "gr": "ἐξελεύσεται"
                },
                "14": {
                    "hb": "משׁפט",
                    "gr": "τὸ κρίμα"
                },
                "15": {
                    "hb": "מעקל",
                    "gr": "διεστραμμένον"
                }
            },
            "5": {
                "1": {
                    "hb": "ראו",
                    "gr": "ἴδετε"
                },
                "2": {
                    "hb": "בגוים =בגדים .wd <2.5>",
                    "gr": "οἱ καταφρονηταί"
                },
                "3": {
                    "hb": "והביטו",
                    "gr": "καὶ ἐπιβλέψατε"
                },
                "4": {
                    "hb": "והתמהו",
                    "gr": "καὶ θαυμάσατε"
                },
                "5": {
                    "hb": "תמהו",
                    "gr": "θαυμάσια {d} καὶ ἀφανίσθητε"
                },
                "6": {
                    "hb": "כי",
                    "gr": "διότι"
                },
                "7": {
                    "hb": "פעל",
                    "gr": "ἔργον"
                },
                "8": {
                    "hb": "פעל",
                    "gr": "ἐγὼ ἐργάζομαι"
                },
                "9": {
                    "hb": "בימיכם",
                    "gr": "ἐν ταῖς ἡμέραις ὑμῶν"
                },
                "10": {
                    "hb": "--+",
                    "gr": "ὃ"
                },
                "11": {
                    "hb": "לא",
                    "gr": "οὐ μὴ"
                },
                "12": {
                    "hb": "תאמינו",
                    "gr": "πιστεύσητε"
                },
                "13": {
                    "hb": "כי",
                    "gr": "ἐάν"
                },
                "14": {
                    "hb": "יספר =%vpa",
                    "gr": "τις ἐκδιηγῆται"
                }
            },
            "6": {
                "1": {
                    "hb": "כי",
                    "gr": "διότι"
                },
                "2": {
                    "hb": "הנני",
                    "gr": "ἰδοὺ ἐγὼ"
                },
                "3": {
                    "hb": "מקים",
                    "gr": "ἐξεγείρω"
                },
                "4": {
                    "hb": "--+",
                    "gr": "ἐφ' ὑμᾶς"
                },
                "5": {
                    "hb": "את הכשׂדים",
                    "gr": "τοὺς χαλδαίους"
                },
                "6": {
                    "hb": "--+",
                    "gr": "τοὺς μαχητάς"
                },
                "7": {
                    "hb": "הגוי",
                    "gr": "τὸ ἔθνος"
                },
                "8": {
                    "hb": "המר",
                    "gr": "τὸ πικρὸν"
                },
                "9": {
                    "hb": "והנמהר",
                    "gr": "καὶ τὸ ταχινὸν"
                },
                "10": {
                    "hb": "ההולך",
                    "gr": "τὸ πορευόμενον"
                },
                "11": {
                    "hb": "למרחבי",
                    "gr": "ἐπὶ τὰ πλάτη"
                },
                "12": {
                    "hb": "ארץ",
                    "gr": "τῆς γῆς"
                },
                "13": {
                    "hb": "לרשׁת",
                    "gr": "τοῦ κατακληρονομῆσαι"
                },
                "14": {
                    "hb": "משׁכנות",
                    "gr": "σκηνώματα"
                },
                "15": {
                    "hb": "לא",
                    "gr": "οὐκ"
                },
                "16": {
                    "hb": "לו",
                    "gr": "αὐτοῦ"
                }
            },
            "7": {
                "1": {
                    "hb": "אים",
                    "gr": "φοβερὸς"
                },
                "2": {
                    "hb": "ונורא",
                    "gr": "καὶ ἐπιφανής"
                },
                "3": {
                    "hb": "הוא",
                    "gr": "ἐστιν"
                },
                "4": {
                    "hb": "ממנו",
                    "gr": "ἐξ αὐτοῦ"
                },
                "5": {
                    "hb": "משׁפטו",
                    "gr": "τὸ κρίμα αὐτοῦ"
                },
                "6": {
                    "hb": "--+",
                    "gr": "ἔσται"
                },
                "7": {
                    "hb": "ושׂאתו =@",
                    "gr": "καὶ τὸ λῆμμα αὐτοῦ"
                },
                "8": {
                    "hb": "--+",
                    "gr": "ἐξ αὐτοῦ"
                },
                "9": {
                    "hb": "יצא",
                    "gr": "ἐξελεύσεται"
                }
            },
            "8": {
                "1": {
                    "hb": "וקלו",
                    "gr": "καὶ ἐξαλοῦνται"
                },
                "2": {
                    "hb": "מנמרים",
                    "gr": "ὑπὲρ παρδάλεις"
                },
                "3": {
                    "hb": "סוסיו",
                    "gr": "οἱ ἵπποι αὐτοῦ"
                },
                "4": {
                    "hb": "וחדו",
                    "gr": "καὶ ὀξύτεροι"
                },
                "5": {
                    "hb": "מזאבי",
                    "gr": "ὑπὲρ τοὺς λύκους"
                },
                "6": {
                    "hb": "ערב =v",
                    "gr": "τῆς ἀραβίας"
                },
                "7": {
                    "hb": "ופשׁו =ופרשׁו",
                    "gr": "καὶ ἐξιππάσονται"
                },
                "8": {
                    "hb": "פרשׁיו",
                    "gr": "οἱ ἱππεῖς αὐτοῦ"
                },
                "9": {
                    "hb": "ופרשׁיו {d}",
                    "gr": "---"
                },
                "10": {
                    "hb": "מרחוק ^ =יבאו",
                    "gr": "καὶ ὁρμήσουσιν"
                },
                "11": {
                    "hb": "^ יבאו =מרחוק",
                    "gr": "μακρόθεν"
                },
                "12": {
                    "hb": "יעפו",
                    "gr": "καὶ πετασθήσονται"
                },
                "13": {
                    "hb": "כנשׁר",
                    "gr": "ὡς ἀετὸς"
                },
                "14": {
                    "hb": "חשׁ",
                    "gr": "πρόθυμος"
                },
                "15": {
                    "hb": "לאכול",
                    "gr": "εἰς τὸ φαγεῖν"
                }
            },
            "9": {
                "1": {
                    "hb": "כלה =כלה =v =@",
                    "gr": "συντέλεια"
                },
                "2": {
                    "hb": "לחמס",
                    "gr": "εἰς ἀσεβεῖς"
                },
                "3": {
                    "hb": "יבוא",
                    "gr": "ἥξει"
                },
                "4": {
                    "hb": "מגמת",
                    "gr": "ἀνθεστηκότας"
                },
                "5": {
                    "hb": "פניהם",
                    "gr": "προσώποις αὐτῶν"
                },
                "6": {
                    "hb": "קדימה",
                    "gr": "ἐξ ἐναντίας"
                },
                "7": {
                    "hb": "ויאסף",
                    "gr": "καὶ συνάξει"
                },
                "8": {
                    "hb": "כחול",
                    "gr": "ὡς ἄμμον"
                },
                "9": {
                    "hb": "שׁבי",
                    "gr": "αἰχμαλωσίαν"
                }
            },
            "10": {
                "1": {
                    "hb": "והוא",
                    "gr": "καὶ αὐτὸς"
                },
                "2": {
                    "hb": "במלכים",
                    "gr": "ἐν βασιλεῦσιν"
                },
                "3": {
                    "hb": "יתקלס",
                    "gr": "ἐντρυφήσει"
                },
                "4": {
                    "hb": "ורזנים",
                    "gr": "καὶ τύραννοι"
                },
                "5": {
                    "hb": "משׂחק",
                    "gr": "παίγνια"
                },
                "6": {
                    "hb": "לו",
                    "gr": "αὐτοῦ"
                },
                "7": {
                    "hb": "הוא",
                    "gr": "καὶ αὐτὸς"
                },
                "8": {
                    "hb": "לכל",
                    "gr": "εἰς πᾶν"
                },
                "9": {
                    "hb": "מבצר",
                    "gr": "ὀχύρωμα"
                },
                "10": {
                    "hb": "ישׂחק",
                    "gr": "ἐμπαίξεται"
                },
                "11": {
                    "hb": "ויצבר",
                    "gr": "καὶ βαλεῖ"
                },
                "12": {
                    "hb": "עפר",
                    "gr": "χῶμα"
                },
                "13": {
                    "hb": "וילכדה",
                    "gr": "καὶ κρατήσει αὐτοῦ"
                }
            },
            "11": {
                "1": {
                    "hb": "אז",
                    "gr": "τότε"
                },
                "2": {
                    "hb": "חלף",
                    "gr": "μεταβαλεῖ"
                },
                "3": {
                    "hb": "רוח",
                    "gr": "τὸ πνεῦμα"
                },
                "4": {
                    "hb": "ויעבר",
                    "gr": "καὶ διελεύσεται"
                },
                "5": {
                    "hb": "ואשׁם",
                    "gr": "καὶ ἐξιλάσεται"
                },
                "6": {
                    "hb": "זו",
                    "gr": "αὕτη"
                },
                "7": {
                    "hb": "כחו",
                    "gr": "ἡ ἰσχὺς"
                },
                "8": {
                    "hb": "לאלהו",
                    "gr": "τῷ θεῷ μου"
                }
            },
            "12": {
                "1": {
                    "hb": "הלוא",
                    "gr": "οὐχὶ"
                },
                "2": {
                    "hb": "אתה",
                    "gr": "σὺ"
                },
                "3": {
                    "hb": "מקדם",
                    "gr": "ἀπ' ἀρχῆς"
                },
                "4": {
                    "hb": "יהוה",
                    "gr": "κύριε"
                },
                "5": {
                    "hb": "אלהי",
                    "gr": "ὁ θεὸς"
                },
                "6": {
                    "hb": "קדשׁי",
                    "gr": "ὁ ἅγιός μου"
                },
                "7": {
                    "hb": "לא",
                    "gr": "καὶ οὐ μὴ"
                },
                "8": {
                    "hb": "נמות",
                    "gr": "ἀποθάνωμεν"
                },
                "9": {
                    "hb": "יהוה",
                    "gr": "κύριε"
                },
                "10": {
                    "hb": "למשׁפט",
                    "gr": "εἰς κρίμα"
                },
                "11": {
                    "hb": "שׂמתו",
                    "gr": "τέταχας αὐτόν"
                },
                "12": {
                    "hb": "וצור =@יצר",
                    "gr": "καὶ ἔπλασέν με"
                },
                "13": {
                    "hb": "להוכיח",
                    "gr": "τοῦ ἐλέγχειν"
                },
                "14": {
                    "hb": "יסדתו =@יסר",
                    "gr": "παιδείαν αὐτοῦ"
                }
            },
            "13": {
                "1": {
                    "hb": "טהור",
                    "gr": "καθαρὸς"
                },
                "2": {
                    "hb": "עינים",
                    "gr": "ὀφθαλμὸς"
                },
                "3": {
                    "hb": "מראות",
                    "gr": "τοῦ μὴ ὁρᾶν"
                },
                "4": {
                    "hb": "רע",
                    "gr": "πονηρά"
                },
                "5": {
                    "hb": "והביט",
                    "gr": "καὶ ἐπιβλέπειν"
                },
                "6": {
                    "hb": "אל",
                    "gr": "ἐπὶ"
                },
                "7": {
                    "hb": "עמל",
                    "gr": "πόνους"
                },
                "8": {
                    "hb": "לא",
                    "gr": "οὐ"
                },
                "9": {
                    "hb": "תוכל",
                    "gr": "δυνήσῃ"
                },
                "10": {
                    "hb": "למה",
                    "gr": "ἵνα τί"
                },
                "11": {
                    "hb": "תביט",
                    "gr": "ἐπιβλέπεις"
                },
                "12": {
                    "hb": "{...}",
                    "gr": "ἐπὶ"
                },
                "13": {
                    "hb": "בוגדים",
                    "gr": "{..pἐπὶ} καταφρονοῦντας"
                },
                "14": {
                    "hb": "תחרישׁ",
                    "gr": "παρασιωπήσῃ"
                },
                "15": {
                    "hb": "בבלע",
                    "gr": "ἐν τῷ καταπίνειν"
                },
                "16": {
                    "hb": "רשׁע",
                    "gr": "ἀσεβῆ"
                },
                "17": {
                    "hb": "צדיק {...?ממנו}",
                    "gr": "τὸν δίκαιον"
                },
                "18": {
                    "hb": "ממנו",
                    "gr": "--- ̣"
                }
            },
            "14": {
                "1": {
                    "hb": "ותעשׂה",
                    "gr": "καὶ ποιήσεις"
                },
                "2": {
                    "hb": "אדם",
                    "gr": "τοὺς ἀνθρώπους"
                },
                "3": {
                    "hb": "כדגי",
                    "gr": "ὡς τοὺς ἰχθύας"
                },
                "4": {
                    "hb": "הים",
                    "gr": "τῆς θαλάσσης"
                },
                "5": {
                    "hb": "כרמשׂ",
                    "gr": "καὶ ὡς τὰ ἑρπετὰ"
                },
                "6": {
                    "hb": "{...}",
                    "gr": "τὰ"
                },
                "7": {
                    "hb": "לא",
                    "gr": "{..pτὰ} οὐκ"
                },
                "8": {
                    "hb": "{...}",
                    "gr": "ἔχοντα"
                },
                "9": {
                    "hb": "משׁל",
                    "gr": "ἡγούμενον"
                },
                "10": {
                    "hb": "בו",
                    "gr": "{..^ἔχοντα}"
                }
            },
            "15": {
                "1": {
                    "hb": "כלה =@כלה =v =@",
                    "gr": "συντέλειαν"
                },
                "2": {
                    "hb": "בחכה",
                    "gr": "ἐν ἀγκίστρῳ"
                },
                "3": {
                    "hb": "העלה",
                    "gr": "ἀνέσπασεν"
                },
                "4": {
                    "hb": "יגרהו",
                    "gr": "καὶ εἵλκυσεν αὐτὸν"
                },
                "5": {
                    "hb": "בחרמו",
                    "gr": "ἐν ἀμφιβλήστρῳ"
                },
                "6": {
                    "hb": "ויאספהו",
                    "gr": "καὶ συνήγαγεν αὐτὸν"
                },
                "7": {
                    "hb": "במכמרתו",
                    "gr": "ἐν ταῖς σαγήναις αὐτοῦ"
                },
                "8": {
                    "hb": "על כן",
                    "gr": "ἕνεκεν τούτου"
                },
                "9": {
                    "hb": "ישׂמח",
                    "gr": "εὐφρανθήσεται"
                },
                "10": {
                    "hb": "ויגיל",
                    "gr": "καὶ χαρήσεται"
                },
                "11": {
                    "hb": "--+",
                    "gr": "ἡ καρδία αὐτοῦ"
                }
            },
            "16": {
                "1": {
                    "hb": "על כן",
                    "gr": "ἕνεκεν τούτου"
                },
                "2": {
                    "hb": "יזבח",
                    "gr": "θύσει"
                },
                "3": {
                    "hb": "לחרמו",
                    "gr": "τῇ σαγήνῃ αὐτοῦ"
                },
                "4": {
                    "hb": "ויקטר",
                    "gr": "καὶ θυμιάσει"
                },
                "5": {
                    "hb": "למכמרתו",
                    "gr": "τῷ ἀμφιβλήστρῳ αὐτοῦ"
                },
                "6": {
                    "hb": "כי",
                    "gr": "ὅτι"
                },
                "7": {
                    "hb": "בהמה",
                    "gr": "ἐν αὐτοῖς"
                },
                "8": {
                    "hb": "שׁמן =v",
                    "gr": "ἐλίπανεν"
                },
                "9": {
                    "hb": "חלקו",
                    "gr": "μερίδα αὐτοῦ"
                },
                "10": {
                    "hb": "ומאכלו",
                    "gr": "καὶ τὰ βρώματα αὐτοῦ"
                },
                "11": {
                    "hb": "בראה =@ברר",
                    "gr": "ἐκλεκτά"
                }
            },
            "17": {
                "1": {
                    "hb": "העל כן",
                    "gr": "διὰ τοῦτο"
                },
                "2": {
                    "hb": "יריק",
                    "gr": "ἀμφιβαλεῖ"
                },
                "3": {
                    "hb": "חרמו",
                    "gr": "τὸ ἀμφίβληστρον αὐτοῦ"
                },
                "4": {
                    "hb": "ותמיד",
                    "gr": "καὶ διὰ παντὸς"
                },
                "5": {
                    "hb": "להרג",
                    "gr": "ἀποκτέννειν"
                },
                "6": {
                    "hb": "גוים",
                    "gr": "ἔθνη"
                },
                "7": {
                    "hb": "לא",
                    "gr": "οὐ"
                },
                "8": {
                    "hb": "יחמול",
                    "gr": "φείσεται"
                }
            }
        },
        "2": {
            "1": {
                "1": {
                    "hb": "על",
                    "gr": "ἐπὶ"
                },
                "2": {
                    "hb": "משׁמרתי",
                    "gr": "τῆς φυλακῆς μου"
                },
                "3": {
                    "hb": "אעמדה",
                    "gr": "στήσομαι"
                },
                "4": {
                    "hb": "ואתיצבה",
                    "gr": "καὶ ἐπιβήσομαι"
                },
                "5": {
                    "hb": "על",
                    "gr": "ἐπὶ"
                },
                "6": {
                    "hb": "מצור =@צור",
                    "gr": "πέτραν"
                },
                "7": {
                    "hb": "ואצפה",
                    "gr": "καὶ ἀποσκοπεύσω"
                },
                "8": {
                    "hb": "לראות",
                    "gr": "τοῦ ἰδεῖν"
                },
                "9": {
                    "hb": "מה",
                    "gr": "τί"
                },
                "10": {
                    "hb": "ידבר",
                    "gr": "λαλήσει"
                },
                "11": {
                    "hb": "בי",
                    "gr": "ἐν ἐμοὶ"
                },
                "12": {
                    "hb": "ומה",
                    "gr": "καὶ τί"
                },
                "13": {
                    "hb": "אשׁיב",
                    "gr": "ἀποκριθῶ"
                },
                "14": {
                    "hb": "על",
                    "gr": "ἐπὶ"
                },
                "15": {
                    "hb": "תוכחתי",
                    "gr": "τὸν ἔλεγχόν μου"
                }
            },
            "2": {
                "1": {
                    "hb": "ויענני",
                    "gr": "καὶ ἀπεκρίθη πρός με"
                },
                "2": {
                    "hb": "יהוה",
                    "gr": "κύριος"
                },
                "3": {
                    "hb": "ויאמר",
                    "gr": "καὶ εἶπεν"
                },
                "4": {
                    "hb": "כתוב",
                    "gr": "γράψον"
                },
                "5": {
                    "hb": "חזון",
                    "gr": "ὅρασιν"
                },
                "6": {
                    "hb": "ובאר =v",
                    "gr": "καὶ σαφῶς"
                },
                "7": {
                    "hb": "על",
                    "gr": "ἐπὶ"
                },
                "8": {
                    "hb": "הלחות",
                    "gr": "πυξίον"
                },
                "9": {
                    "hb": "למען",
                    "gr": "ὅπως"
                },
                "10": {
                    "hb": "ירוץ",
                    "gr": "διώκῃ"
                },
                "11": {
                    "hb": "קורא",
                    "gr": "ὁ ἀναγινώσκων"
                },
                "12": {
                    "hb": "בו",
                    "gr": "αὐτά"
                }
            },
            "3": {
                "1": {
                    "hb": "כי",
                    "gr": "διότι"
                },
                "2": {
                    "hb": "עוד",
                    "gr": "ἔτι"
                },
                "3": {
                    "hb": "חזון",
                    "gr": "ὅρασις"
                },
                "4": {
                    "hb": "למועד",
                    "gr": "εἰς καιρὸν"
                },
                "5": {
                    "hb": "ויפח =@יפע .xע",
                    "gr": "καὶ ἀνατελεῖ"
                },
                "6": {
                    "hb": "לקץ",
                    "gr": "εἰς πέρας"
                },
                "7": {
                    "hb": "ולא",
                    "gr": "καὶ οὐκ"
                },
                "8": {
                    "hb": "יכזב =?לכזב",
                    "gr": "εἰς κενόν"
                },
                "9": {
                    "hb": "אם",
                    "gr": "ἐὰν"
                },
                "10": {
                    "hb": "יתמהמה",
                    "gr": "ὑστερήσῃ"
                },
                "11": {
                    "hb": "חכה",
                    "gr": "ὑπόμεινον"
                },
                "12": {
                    "hb": "לו",
                    "gr": "αὐτόν"
                },
                "13": {
                    "hb": "כי",
                    "gr": "ὅτι"
                },
                "14": {
                    "hb": "בא {!}pd",
                    "gr": "ἐρχόμενος"
                },
                "15": {
                    "hb": "יבא {!}pd",
                    "gr": "ἥξει"
                },
                "16": {
                    "hb": "לא",
                    "gr": "καὶ οὐ μὴ"
                },
                "17": {
                    "hb": "יאחר",
                    "gr": "χρονίσῃ"
                }
            },
            "4": {
                "1": {
                    "hb": "הנה =הן",
                    "gr": "ἐὰν"
                },
                "2": {
                    "hb": "עפלה =@?עלף .m",
                    "gr": "ὑποστείληται"
                },
                "3": {
                    "hb": "לא",
                    "gr": "οὐκ"
                },
                "4": {
                    "hb": "ישׁרה",
                    "gr": "εὐδοκεῖ"
                },
                "5": {
                    "hb": "נפשׁו",
                    "gr": "ἡ ψυχή μου"
                },
                "6": {
                    "hb": "בו",
                    "gr": "ἐν αὐτῷ"
                },
                "7": {
                    "hb": "וצדיק",
                    "gr": "ὁ δὲ ^ δίκαιος"
                },
                "8": {
                    "hb": "באמונתו =%p",
                    "gr": "ἐκ πίστεώς μου"
                },
                "9": {
                    "hb": "יחיה",
                    "gr": "ζήσεται"
                }
            },
            "5": {
                "1": {
                    "hb": "{...}",
                    "gr": "ὁ"
                },
                "2": {
                    "hb": "ואף כי",
                    "gr": "δὲ"
                },
                "3": {
                    "hb": "היין",
                    "gr": "{...ὁ} κατοινωμένος"
                },
                "4": {
                    "hb": "בוגד",
                    "gr": "καὶ καταφρονητὴς"
                },
                "5": {
                    "hb": "גבר",
                    "gr": "ἀνὴρ"
                },
                "6": {
                    "hb": "יהיר",
                    "gr": "ἀλάζων"
                },
                "7": {
                    "hb": "ולא",
                    "gr": "οὐδὲν μὴ"
                },
                "8": {
                    "hb": "ינוה",
                    "gr": "περάνῃ"
                },
                "9": {
                    "hb": "אשׁר",
                    "gr": "ὃς"
                },
                "10": {
                    "hb": "הרחיב",
                    "gr": "ἐπλάτυνεν"
                },
                "11": {
                    "hb": "כשׁאול",
                    "gr": "καθὼς ὁ ᾅδης"
                },
                "12": {
                    "hb": "נפשׁו",
                    "gr": "τὴν ψυχὴν αὐτοῦ"
                },
                "13": {
                    "hb": "והוא",
                    "gr": "καὶ οὗτος"
                },
                "14": {
                    "hb": "כמות",
                    "gr": "ὡς θάνατος"
                },
                "15": {
                    "hb": "ולא",
                    "gr": "οὐκ"
                },
                "16": {
                    "hb": "ישׂבע",
                    "gr": "ἐμπιπλάμενος"
                },
                "17": {
                    "hb": "ויאסף",
                    "gr": "καὶ ἐπισυνάξει"
                },
                "18": {
                    "hb": "אליו",
                    "gr": "ἐπ' αὐτὸν"
                },
                "19": {
                    "hb": "כל",
                    "gr": "πάντα"
                },
                "20": {
                    "hb": "הגוים",
                    "gr": "τὰ ἔθνη"
                },
                "21": {
                    "hb": "ויקבץ",
                    "gr": "καὶ εἰσδέξεται"
                },
                "22": {
                    "hb": "אליו",
                    "gr": "πρὸς αὐτὸν"
                },
                "23": {
                    "hb": "כל",
                    "gr": "πάντας"
                },
                "24": {
                    "hb": "העמים",
                    "gr": "τοὺς λαούς"
                }
            },
            "6": {
                "1": {
                    "hb": "הלוא",
                    "gr": "οὐχὶ"
                },
                "2": {
                    "hb": "אלה",
                    "gr": "ταῦτα"
                },
                "3": {
                    "hb": "כלם",
                    "gr": "πάντα"
                },
                "4": {
                    "hb": "עליו ^ =משׁל",
                    "gr": "παραβολὴν"
                },
                "5": {
                    "hb": "^ משׁל =עליו",
                    "gr": "κατ' αὐτοῦ"
                },
                "6": {
                    "hb": "ישׂאו",
                    "gr": "λήμψονται"
                },
                "7": {
                    "hb": "ומליצה ^ ? =וחידות",
                    "gr": "καὶ πρόβλημα"
                },
                "8": {
                    "hb": "^ ? חידות =מליצה",
                    "gr": "εἰς διήγησιν"
                },
                "9": {
                    "hb": "לו",
                    "gr": "αὐτοῦ"
                },
                "10": {
                    "hb": "ויאמר",
                    "gr": "καὶ ἐροῦσιν"
                },
                "11": {
                    "hb": "הוי",
                    "gr": "οὐαὶ"
                },
                "12": {
                    "hb": "המרבה",
                    "gr": "ὁ πληθύνων"
                },
                "13": {
                    "hb": "--+",
                    "gr": "ἑαυτῷ"
                },
                "14": {
                    "hb": "{...}",
                    "gr": "τὰ"
                },
                "15": {
                    "hb": "לא",
                    "gr": "οὐκ"
                },
                "16": {
                    "hb": "לו",
                    "gr": "{...τὰ} ὄντα αὐτοῦ"
                },
                "17": {
                    "hb": "עד",
                    "gr": "ἕως"
                },
                "18": {
                    "hb": "מתי",
                    "gr": "τίνος"
                },
                "19": {
                    "hb": "ומכביד",
                    "gr": "καὶ βαρύνων"
                },
                "20": {
                    "hb": "עליו =עלו",
                    "gr": "τὸν κλοιὸν αὐτοῦ"
                },
                "21": {
                    "hb": "עבטיט",
                    "gr": "στιβαρῶς"
                }
            },
            "7": {
                "1": {
                    "hb": "הלוא =?כי",
                    "gr": "ὅτι"
                },
                "2": {
                    "hb": "פתע",
                    "gr": "ἐξαίφνης"
                },
                "3": {
                    "hb": "יקומו",
                    "gr": "ἀναστήσονται"
                },
                "4": {
                    "hb": "נשׁכיך",
                    "gr": "δάκνοντες αὐτόν"
                },
                "5": {
                    "hb": "ויקצו",
                    "gr": "καὶ ἐκνήψουσιν"
                },
                "6": {
                    "hb": "מזעזעיך",
                    "gr": "οἱ ἐπίβουλοί σου"
                },
                "7": {
                    "hb": "והיית",
                    "gr": "καὶ ἔσῃ"
                },
                "8": {
                    "hb": "למשׁסות",
                    "gr": "εἰς διαρπαγὴν"
                },
                "9": {
                    "hb": "למו",
                    "gr": "αὐτοῖς"
                }
            },
            "8": {
                "1": {
                    "hb": "כי",
                    "gr": "διότι"
                },
                "2": {
                    "hb": "אתה",
                    "gr": "σὺ"
                },
                "3": {
                    "hb": "שׁלות",
                    "gr": "ἐσκύλευσας"
                },
                "4": {
                    "hb": "גוים",
                    "gr": "ἔθνη"
                },
                "5": {
                    "hb": "רבים",
                    "gr": "πολλά"
                },
                "6": {
                    "hb": "ישׁלוך",
                    "gr": "σκυλεύσουσίν σε"
                },
                "7": {
                    "hb": "כל",
                    "gr": "πάντες"
                },
                "8": {
                    "hb": "יתר",
                    "gr": "οἱ ὑπολελειμμένοι"
                },
                "9": {
                    "hb": "עמים",
                    "gr": "λαοὶ"
                },
                "10": {
                    "hb": "מדמי",
                    "gr": "δι' αἵματα"
                },
                "11": {
                    "hb": "אדם",
                    "gr": "ἀνθρώπων"
                },
                "12": {
                    "hb": "וחמס",
                    "gr": "καὶ ἀσεβείας"
                },
                "13": {
                    "hb": "ארץ",
                    "gr": "γῆς"
                },
                "14": {
                    "hb": "קריה",
                    "gr": "καὶ πόλεως"
                },
                "15": {
                    "hb": "וכל",
                    "gr": "καὶ πάντων"
                },
                "16": {
                    "hb": "ישׁבי",
                    "gr": "τῶν κατοικούντων"
                },
                "17": {
                    "hb": "בה",
                    "gr": "αὐτήν"
                }
            },
            "9": {
                "1": {
                    "hb": "הוי",
                    "gr": "ὦ"
                },
                "2": {
                    "hb": "בצע",
                    "gr": "ὁ πλεονεκτῶν"
                },
                "3": {
                    "hb": "בצע",
                    "gr": "πλεονεξίαν"
                },
                "4": {
                    "hb": "רע",
                    "gr": "κακὴν"
                },
                "5": {
                    "hb": "לביתו",
                    "gr": "τῷ οἴκῳ αὐτοῦ"
                },
                "6": {
                    "hb": "לשׂום",
                    "gr": "τοῦ τάξαι"
                },
                "7": {
                    "hb": "במרום",
                    "gr": "εἰς ὕψος"
                },
                "8": {
                    "hb": "קנו",
                    "gr": "νοσσιὰν αὐτοῦ"
                },
                "9": {
                    "hb": "להנצל",
                    "gr": "τοῦ ἐκσπασθῆναι"
                },
                "10": {
                    "hb": "מכף",
                    "gr": "ἐκ χειρὸς"
                },
                "11": {
                    "hb": "רע",
                    "gr": "κακῶν"
                }
            },
            "10": {
                "1": {
                    "hb": "יעצת",
                    "gr": "ἐβουλεύσω"
                },
                "2": {
                    "hb": "בשׁת",
                    "gr": "αἰσχύνην"
                },
                "3": {
                    "hb": "לביתך",
                    "gr": "τῷ οἴκῳ σου"
                },
                "4": {
                    "hb": "קצות =v",
                    "gr": "συνεπέρανας"
                },
                "5": {
                    "hb": "עמים",
                    "gr": "λαοὺς"
                },
                "6": {
                    "hb": "רבים",
                    "gr": "πολλούς"
                },
                "7": {
                    "hb": "וחוטא",
                    "gr": "καὶ ἐξήμαρτεν"
                },
                "8": {
                    "hb": "נפשׁך",
                    "gr": "ἡ ψυχή σου"
                }
            },
            "11": {
                "1": {
                    "hb": "כי",
                    "gr": "διότι"
                },
                "2": {
                    "hb": "אבן",
                    "gr": "λίθος"
                },
                "3": {
                    "hb": "מקיר",
                    "gr": "ἐκ τοίχου"
                },
                "4": {
                    "hb": "תזעק",
                    "gr": "βοήσεται"
                },
                "5": {
                    "hb": "וכפיס",
                    "gr": "καὶ κάνθαρος"
                },
                "6": {
                    "hb": "מעץ",
                    "gr": "ἐκ ξύλου"
                },
                "7": {
                    "hb": "יעננה",
                    "gr": "φθέγξεται αὐτά"
                }
            },
            "12": {
                "1": {
                    "hb": "הוי",
                    "gr": "οὐαὶ"
                },
                "2": {
                    "hb": "בנה",
                    "gr": "ὁ οἰκοδομῶν"
                },
                "3": {
                    "hb": "עיר",
                    "gr": "πόλιν"
                },
                "4": {
                    "hb": "בדמים",
                    "gr": "ἐν αἵμασιν"
                },
                "5": {
                    "hb": "וכונן",
                    "gr": "καὶ ἑτοιμάζων"
                },
                "6": {
                    "hb": "קריה",
                    "gr": "πόλιν"
                },
                "7": {
                    "hb": "בעולה",
                    "gr": "ἐν ἀδικίαις"
                }
            },
            "13": {
                "1": {
                    "hb": "הלוא",
                    "gr": "οὐ"
                },
                "2": {
                    "hb": "הנה",
                    "gr": "ταῦτά ἐστιν"
                },
                "3": {
                    "hb": "מאת",
                    "gr": "παρὰ"
                },
                "4": {
                    "hb": "יהוה",
                    "gr": "κυρίου"
                },
                "5": {
                    "hb": "צבאות",
                    "gr": "παντοκράτορος"
                },
                "6": {
                    "hb": "וייגעו",
                    "gr": "καὶ ἐξέλιπον"
                },
                "7": {
                    "hb": "עמים",
                    "gr": "λαοὶ"
                },
                "8": {
                    "hb": "בדי =%p-",
                    "gr": "ἱκανοὶ"
                },
                "9": {
                    "hb": "אשׁ =%pט",
                    "gr": "ἐν πυρί"
                },
                "10": {
                    "hb": "ולאמים",
                    "gr": "καὶ ἔθνη"
                },
                "11": {
                    "hb": "בדי ריק =רבים .j",
                    "gr": "πολλὰ"
                },
                "12": {
                    "hb": "יעפו",
                    "gr": "ὠλιγοψύχησαν"
                }
            },
            "14": {
                "1": {
                    "hb": "כי",
                    "gr": "ὅτι"
                },
                "2": {
                    "hb": "תמלא",
                    "gr": "πλησθήσεται"
                },
                "3": {
                    "hb": "הארץ",
                    "gr": "ἡ γῆ"
                },
                "4": {
                    "hb": "לדעת",
                    "gr": "τοῦ γνῶναι"
                },
                "5": {
                    "hb": "את כבוד",
                    "gr": "τὴν δόξαν"
                },
                "6": {
                    "hb": "יהוה",
                    "gr": "κυρίου"
                },
                "7": {
                    "hb": "כמים",
                    "gr": "ὡς ὕδωρ"
                },
                "8": {
                    "hb": "יכסו",
                    "gr": "κατακαλύψει"
                },
                "9": {
                    "hb": "על ים =עליהם .j",
                    "gr": "αὐτούς"
                }
            },
            "15": {
                "1": {
                    "hb": "הוי",
                    "gr": "ὦ"
                },
                "2": {
                    "hb": "משׁקה",
                    "gr": "ὁ ποτίζων"
                },
                "3": {
                    "hb": "רעהו",
                    "gr": "τὸν πλησίον αὐτοῦ"
                },
                "4": {
                    "hb": "מספח =v",
                    "gr": "ἀνατροπῇ"
                },
                "5": {
                    "hb": "חמתך",
                    "gr": "θολερᾷ"
                },
                "6": {
                    "hb": "ואף",
                    "gr": "καὶ"
                },
                "7": {
                    "hb": "שׁכר",
                    "gr": "μεθύσκων"
                },
                "8": {
                    "hb": "למען",
                    "gr": "ὅπως"
                },
                "9": {
                    "hb": "הביט",
                    "gr": "ἐπιβλέπῃ"
                },
                "10": {
                    "hb": "על",
                    "gr": "ἐπὶ"
                },
                "11": {
                    "hb": "מעוריהם =@מערה",
                    "gr": "τὰ σπήλαια αὐτῶν"
                }
            },
            "16": {
                "1": {
                    "hb": "שׂבעת =v",
                    "gr": "πλησμονὴν"
                },
                "2": {
                    "hb": "קלון",
                    "gr": "ἀτιμίας"
                },
                "3": {
                    "hb": "מכבוד",
                    "gr": "ἐκ δόξης"
                },
                "4": {
                    "hb": "שׁתה",
                    "gr": "πίε"
                },
                "5": {
                    "hb": "גם",
                    "gr": "καὶ"
                },
                "6": {
                    "hb": "אתה",
                    "gr": "σὺ"
                },
                "7": {
                    "hb": "והערל =והרעל .m",
                    "gr": "καὶ διασαλεύθητι {d} καὶ σείσθητι"
                },
                "8": {
                    "hb": "תסוב",
                    "gr": "ἐκύκλωσεν"
                },
                "9": {
                    "hb": "עליך",
                    "gr": "ἐπὶ σὲ"
                },
                "10": {
                    "hb": "כוס",
                    "gr": "ποτήριον"
                },
                "11": {
                    "hb": "ימין",
                    "gr": "δεξιᾶς"
                },
                "12": {
                    "hb": "יהוה",
                    "gr": "κυρίου"
                },
                "13": {
                    "hb": "וקיקלון =@קוה .s",
                    "gr": "καὶ συνήχθη ἀτιμία"
                },
                "14": {
                    "hb": "על",
                    "gr": "ἐπὶ"
                },
                "15": {
                    "hb": "כבודך",
                    "gr": "τὴν δόξαν σου"
                }
            },
            "17": {
                "1": {
                    "hb": "כי",
                    "gr": "διότι"
                },
                "2": {
                    "hb": "חמס",
                    "gr": "ἀσέβεια"
                },
                "3": {
                    "hb": "לבנון",
                    "gr": "τοῦ λιβάνου"
                },
                "4": {
                    "hb": "יכסך",
                    "gr": "καλύψει σε"
                },
                "5": {
                    "hb": "ושׁד",
                    "gr": "καὶ ταλαιπωρία"
                },
                "6": {
                    "hb": "בהמות",
                    "gr": "θηρίων"
                },
                "7": {
                    "hb": "יחיתן",
                    "gr": "πτοήσει σε"
                },
                "8": {
                    "hb": "מדמי",
                    "gr": "διὰ αἵματα"
                },
                "9": {
                    "hb": "אדם",
                    "gr": "ἀνθρώπων"
                },
                "10": {
                    "hb": "וחמס",
                    "gr": "καὶ ἀσεβείας"
                },
                "11": {
                    "hb": "ארץ",
                    "gr": "γῆς"
                },
                "12": {
                    "hb": "קריה",
                    "gr": "καὶ πόλεως"
                },
                "13": {
                    "hb": "וכל",
                    "gr": "καὶ πάντων"
                },
                "14": {
                    "hb": "ישׁבי",
                    "gr": "τῶν κατοικούντων"
                },
                "15": {
                    "hb": "בה",
                    "gr": "αὐτήν"
                }
            },
            "18": {
                "1": {
                    "hb": "מה",
                    "gr": "τί"
                },
                "2": {
                    "hb": "הועיל",
                    "gr": "ὠφελεῖ"
                },
                "3": {
                    "hb": "פסל",
                    "gr": "γλυπτόν"
                },
                "4": {
                    "hb": "כי",
                    "gr": "ὅτι"
                },
                "5": {
                    "hb": "פסלו",
                    "gr": "ἔγλυψαν αὐτό"
                },
                "6": {
                    "hb": "יצרו =v",
                    "gr": "ἔπλασαν αὐτὸ"
                },
                "7": {
                    "hb": "מסכה",
                    "gr": "χώνευμα"
                },
                "8": {
                    "hb": "ומורה =@מראה",
                    "gr": "φαντασίαν"
                },
                "9": {
                    "hb": "שׁקר",
                    "gr": "ψευδῆ"
                },
                "10": {
                    "hb": "כי",
                    "gr": "ὅτι"
                },
                "11": {
                    "hb": "בטח",
                    "gr": "πέποιθεν"
                },
                "12": {
                    "hb": "יצר",
                    "gr": "ὁ πλάσας"
                },
                "13": {
                    "hb": "יצרו ^ =עליו",
                    "gr": "ἐπὶ"
                },
                "14": {
                    "hb": "^ עליו =יצרו",
                    "gr": "τὸ πλάσμα αὐτοῦ"
                },
                "15": {
                    "hb": "לעשׂות",
                    "gr": "τοῦ ποιῆσαι"
                },
                "16": {
                    "hb": "אלילים",
                    "gr": "εἴδωλα"
                },
                "17": {
                    "hb": "אלמים",
                    "gr": "κωφά"
                }
            },
            "19": {
                "1": {
                    "hb": "הוי",
                    "gr": "οὐαὶ"
                },
                "2": {
                    "hb": "אמר",
                    "gr": "ὁ λέγων"
                },
                "3": {
                    "hb": "לעץ",
                    "gr": "τῷ ξύλῳ"
                },
                "4": {
                    "hb": "הקיצה",
                    "gr": "ἔκνηψον"
                },
                "5": {
                    "hb": "עורי",
                    "gr": "ἐξεγέρθητι"
                },
                "6": {
                    "hb": "לאבן",
                    "gr": "καὶ τῷ λίθῳ"
                },
                "7": {
                    "hb": "דומם =@רום .dr",
                    "gr": "ὑψώθητι"
                },
                "8": {
                    "hb": "הוא",
                    "gr": "καὶ αὐτό ἐστιν"
                },
                "9": {
                    "hb": "יורה =@מראה",
                    "gr": "φαντασία"
                },
                "10": {
                    "hb": "הנה",
                    "gr": "τοῦτο δέ"
                },
                "11": {
                    "hb": "הוא",
                    "gr": "ἐστιν"
                },
                "12": {
                    "hb": "תפושׂ",
                    "gr": "ἔλασμα"
                },
                "13": {
                    "hb": "זהב",
                    "gr": "χρυσίου"
                },
                "14": {
                    "hb": "וכסף",
                    "gr": "καὶ ἀργυρίου"
                },
                "15": {
                    "hb": "וכל",
                    "gr": "καὶ πᾶν"
                },
                "16": {
                    "hb": "רוח",
                    "gr": "πνεῦμα"
                },
                "17": {
                    "hb": "אין",
                    "gr": "οὐκ ἔστιν"
                },
                "18": {
                    "hb": "בקרבו",
                    "gr": "ἐν αὐτῷ"
                }
            },
            "20": {
                "1": {
                    "hb": "ויהוה",
                    "gr": "ὁ δὲ ^ κύριος"
                },
                "2": {
                    "hb": "בהיכל",
                    "gr": "ἐν ναῷ"
                },
                "3": {
                    "hb": "קדשׁו",
                    "gr": "ἁγίῳ αὐτοῦ"
                },
                "4": {
                    "hb": "הס",
                    "gr": "εὐλαβείσθω"
                },
                "5": {
                    "hb": "מפניו",
                    "gr": "ἀπὸ προσώπου αὐτοῦ"
                },
                "6": {
                    "hb": "כל",
                    "gr": "πᾶσα"
                },
                "7": {
                    "hb": "הארץ",
                    "gr": "ἡ γῆ"
                }
            }
        },
        "3": {
            "1": {
                "1": {
                    "hb": "תפלה",
                    "gr": "προσευχὴ"
                },
                "2": {
                    "hb": "לחבקוק",
                    "gr": "αμβακουμ"
                },
                "3": {
                    "hb": "הנביא",
                    "gr": "τοῦ προφήτου"
                },
                "4": {
                    "hb": "על",
                    "gr": "μετὰ"
                },
                "5": {
                    "hb": "שׁגינות =?נגינות <3.19>",
                    "gr": "ᾠδῆς"
                }
            },
            "2": {
                "1": {
                    "hb": "יהוה",
                    "gr": "κύριε"
                },
                "2": {
                    "hb": "שׁמעתי",
                    "gr": "εἰσακήκοα"
                },
                "3": {
                    "hb": "שׁמעך",
                    "gr": "τὴν ἀκοήν σου"
                },
                "4": {
                    "hb": "יראתי ={d}@ראה",
                    "gr": "καὶ ἐφοβήθην {d} κατενόησα {d} ʹ"
                },
                "5": {
                    "hb": "#",
                    "gr": "{...καὶ ἐξέστην}"
                },
                "6": {
                    "hb": "יהוה",
                    "gr": "---"
                },
                "7": {
                    "hb": "פעלך",
                    "gr": "τὰ ἔργα σου"
                },
                "8": {
                    "hb": "{...}",
                    "gr": "καὶ ἐξέστην"
                },
                "9": {
                    "hb": "בקרב",
                    "gr": "ἐν μέσῳ"
                },
                "10": {
                    "hb": "שׁנים =v",
                    "gr": "δύο"
                },
                "11": {
                    "hb": "חייהו =v",
                    "gr": "ζῴων"
                },
                "12": {
                    "hb": "--+",
                    "gr": "γνωσθήσῃ"
                },
                "13": {
                    "hb": "בקרב =v",
                    "gr": "ἐν τῷ ἐγγίζειν {d} {...ἐν τῷ ʹ"
                },
                "14": {
                    "hb": "#",
                    "gr": "παρεῖναἰ"
                },
                "15": {
                    "hb": "שׁנים",
                    "gr": "τὰ ἔτη {d} {...τὸν καιρὸν}"
                },
                "16": {
                    "hb": "תודיע",
                    "gr": "ἐπιγνωσθήσῃ {d} {...ἀναδειχθήσῃ}"
                },
                "17": {
                    "hb": "{...}",
                    "gr": "ἐν τῷ παρεῖναι"
                },
                "18": {
                    "hb": "{...}",
                    "gr": "τὸν καιρὸν"
                },
                "19": {
                    "hb": "{...}",
                    "gr": "ἀναδειχθήσῃ"
                },
                "20": {
                    "hb": "{...}",
                    "gr": "ἐν τῷ ταραχθῆναι"
                },
                "21": {
                    "hb": "{...}",
                    "gr": "τὴν ψυχήν μου"
                },
                "22": {
                    "hb": "ברגז",
                    "gr": "{...ἐν τῷ ταραχθῆναι}{d} ἐν ὀργῇ"
                },
                "23": {
                    "hb": "רחם ={d}רוחי",
                    "gr": "{...τὴν ψυχήν μου} {d} ἐλέους"
                },
                "24": {
                    "hb": "תזכור",
                    "gr": "μνησθήσῃ"
                }
            },
            "3": {
                "1": {
                    "hb": "אלוה",
                    "gr": "ὁ θεὸς"
                },
                "2": {
                    "hb": "מתימן",
                    "gr": "ἐκ θαιμαν"
                },
                "3": {
                    "hb": "יבוא",
                    "gr": "ἥξει"
                },
                "4": {
                    "hb": "וקדושׁ",
                    "gr": "καὶ ὁ ἅγιος"
                },
                "5": {
                    "hb": "מהר",
                    "gr": "ἐξ ὄρους"
                },
                "6": {
                    "hb": "פארן =פארה",
                    "gr": "κατασκίου δασέος"
                },
                "7": {
                    "hb": "סלה",
                    "gr": "διάψαλμα"
                },
                "8": {
                    "hb": "כסה",
                    "gr": "ἐκάλυψεν"
                },
                "9": {
                    "hb": "שׁמים",
                    "gr": "οὐρανοὺς"
                },
                "10": {
                    "hb": "הודו",
                    "gr": "ἡ ἀρετὴ αὐτοῦ"
                },
                "11": {
                    "hb": "ותהלתו",
                    "gr": "καὶ αἰνέσεως αὐτοῦ"
                },
                "12": {
                    "hb": "מלאה",
                    "gr": "πλήρης"
                },
                "13": {
                    "hb": "הארץ",
                    "gr": "ἡ γῆ"
                }
            },
            "4": {
                "1": {
                    "hb": "ונגה",
                    "gr": "καὶ φέγγος αὐτοῦ"
                },
                "2": {
                    "hb": "כאור",
                    "gr": "ὡς φῶς"
                },
                "3": {
                    "hb": "תהיה",
                    "gr": "ἔσται"
                },
                "4": {
                    "hb": "קרנים",
                    "gr": "κέρατα"
                },
                "5": {
                    "hb": "מידו לו",
                    "gr": "ἐν χερσὶν αὐτοῦ"
                },
                "6": {
                    "hb": "ושׁם =vs",
                    "gr": "καὶ ἔθετο"
                },
                "7": {
                    "hb": "חביון =@חבב",
                    "gr": "ἀγάπησιν"
                },
                "8": {
                    "hb": "*עזה **עזו",
                    "gr": "κραταιὰν {d} ἰσχύος αὐτοῦ"
                }
            },
            "5": {
                "1": {
                    "hb": "לפניו",
                    "gr": "πρὸ προσώπου αὐτοῦ"
                },
                "2": {
                    "hb": "ילך",
                    "gr": "πορεύσεται"
                },
                "3": {
                    "hb": "דבר =v",
                    "gr": "λόγος"
                },
                "4": {
                    "hb": "ויצא",
                    "gr": "καὶ ἐξελεύσεται"
                },
                "5": {
                    "hb": "רשׁף =?שׂרוך",
                    "gr": "ἐν πεδίλοις"
                },
                "6": {
                    "hb": "לרגליו",
                    "gr": "οἱ πόδες αὐτοῦ"
                }
            },
            "6": {
                "1": {
                    "hb": "עמד",
                    "gr": "ἔστη"
                },
                "2": {
                    "hb": "וימדד =@נוד",
                    "gr": "καὶ ἐσαλεύθη"
                },
                "3": {
                    "hb": "ארץ",
                    "gr": "ἡ γῆ"
                },
                "4": {
                    "hb": "ראה",
                    "gr": "ἐπέβλεψεν"
                },
                "5": {
                    "hb": "ויתר =ויתך <na1.6>",
                    "gr": "καὶ διετάκη"
                },
                "6": {
                    "hb": "גוים",
                    "gr": "ἔθνη"
                },
                "7": {
                    "hb": "ויתפצצו <na1.6>",
                    "gr": "διεθρύβη"
                },
                "8": {
                    "hb": "הררי",
                    "gr": "τὰ ὄρη"
                },
                "9": {
                    "hb": "עד",
                    "gr": "βίᾳ"
                },
                "10": {
                    "hb": "שׁחו",
                    "gr": "ἐτάκησαν"
                },
                "11": {
                    "hb": "גבעות",
                    "gr": "βουνοὶ"
                },
                "12": {
                    "hb": "עולם",
                    "gr": "αἰώνιοι"
                },
                "13": {
                    "hb": "הליכות",
                    "gr": "πορείας [7]"
                },
                "14": {
                    "hb": "עולם",
                    "gr": "αἰωνίας [7]"
                },
                "15": {
                    "hb": "לו",
                    "gr": "αὐτοῦ [7]"
                }
            },
            "7": {
                "1": {
                    "hb": "תחת",
                    "gr": "ἀντὶ"
                },
                "2": {
                    "hb": "און",
                    "gr": "κόπων"
                },
                "3": {
                    "hb": "ראיתי",
                    "gr": "εἶδον"
                },
                "4": {
                    "hb": "אהלי",
                    "gr": "σκηνώματα"
                },
                "5": {
                    "hb": "כושׁן",
                    "gr": "αἰθιόπων"
                },
                "6": {
                    "hb": "ירגזון",
                    "gr": "πτοηθήσονται"
                },
                "7": {
                    "hb": "יריעות",
                    "gr": "καὶ αἱ σκηναὶ"
                },
                "8": {
                    "hb": "ארץ",
                    "gr": "γῆς"
                },
                "9": {
                    "hb": "מדין",
                    "gr": "μαδιαμ"
                }
            },
            "8": {
                "1": {
                    "hb": "הבנהרים",
                    "gr": "μὴ ἐν ποταμοῖς"
                },
                "2": {
                    "hb": "חרה",
                    "gr": "ὠργίσθης"
                },
                "3": {
                    "hb": "יהוה",
                    "gr": "κύριε"
                },
                "4": {
                    "hb": "אם",
                    "gr": "ἢ"
                },
                "5": {
                    "hb": "בנהרים",
                    "gr": "ἐν ποταμοῖς"
                },
                "6": {
                    "hb": "אפך",
                    "gr": "ὁ θυμός σου"
                },
                "7": {
                    "hb": "אם",
                    "gr": "ἢ"
                },
                "8": {
                    "hb": "בים",
                    "gr": "ἐν θαλάσσῃ"
                },
                "9": {
                    "hb": "עברתך",
                    "gr": "τὸ ὅρμημά σου"
                },
                "10": {
                    "hb": "כי",
                    "gr": "ὅτι"
                },
                "11": {
                    "hb": "תרכב",
                    "gr": "ἐπιβήσῃ"
                },
                "12": {
                    "hb": "על",
                    "gr": "ἐπὶ"
                },
                "13": {
                    "hb": "סוסיך",
                    "gr": "τοὺς ἵππους σου"
                },
                "14": {
                    "hb": "מרכבתיך",
                    "gr": "καὶ ἡ ἱππασία σου"
                },
                "15": {
                    "hb": "ישׁועה",
                    "gr": "σωτηρία"
                }
            },
            "9": {
                "1": {
                    "hb": "עריה",
                    "gr": "ἐντείνων"
                },
                "2": {
                    "hb": "תעור =תעיר .wy",
                    "gr": "ἐντενεῖς"
                },
                "3": {
                    "hb": "קשׁתך",
                    "gr": "τὸ τόξον σου"
                },
                "4": {
                    "hb": "שׁבעות",
                    "gr": "---"
                },
                "5": {
                    "hb": "{...}",
                    "gr": "ἐπὶ"
                },
                "6": {
                    "hb": "מטות",
                    "gr": "{..pἐπὶ} τὰ σκῆπτρα"
                },
                "7": {
                    "hb": "אמר",
                    "gr": "λέγει"
                },
                "8": {
                    "hb": "--+",
                    "gr": "κύριος"
                },
                "9": {
                    "hb": "סלה",
                    "gr": "διάψαλμα"
                },
                "10": {
                    "hb": "נהרות",
                    "gr": "ποταμῶν"
                },
                "11": {
                    "hb": "תבקע =%vap",
                    "gr": "ῥαγήσεται"
                },
                "12": {
                    "hb": "ארץ",
                    "gr": "γῆ"
                }
            },
            "10": {
                "1": {
                    "hb": "ראוך",
                    "gr": "ὄψονταί σε"
                },
                "2": {
                    "hb": "יחילו",
                    "gr": "καὶ ὠδινήσουσιν"
                },
                "3": {
                    "hb": "הרים =??",
                    "gr": "λαοί"
                },
                "4": {
                    "hb": "זרם =v",
                    "gr": "σκορπίζων"
                },
                "5": {
                    "hb": "מים",
                    "gr": "ὕδατα"
                },
                "6": {
                    "hb": "עבר =v",
                    "gr": "πορείας αὐτοῦ"
                },
                "7": {
                    "hb": "נתן",
                    "gr": "ἔδωκεν"
                },
                "8": {
                    "hb": "תהום",
                    "gr": "ἡ ἄβυσσος"
                },
                "9": {
                    "hb": "קולו",
                    "gr": "φωνὴν αὐτῆς"
                },
                "10": {
                    "hb": "רום",
                    "gr": "ὕψος"
                },
                "11": {
                    "hb": "ידיהו =@ראה .dr",
                    "gr": "φαντασίας αὐτῆς"
                },
                "12": {
                    "hb": "נשׂא =v =%vap",
                    "gr": "ἐπήρθη"
                }
            },
            "11": {
                "1": {
                    "hb": "שׁמשׁ",
                    "gr": "ὁ ἥλιος"
                },
                "2": {
                    "hb": "ירח",
                    "gr": "καὶ ἡ σελήνη"
                },
                "3": {
                    "hb": "עמד",
                    "gr": "ἔστη"
                },
                "4": {
                    "hb": "זבלה",
                    "gr": "ἐν τῇ τάξει αὐτῆς"
                },
                "5": {
                    "hb": "לאור",
                    "gr": "εἰς φῶς"
                },
                "6": {
                    "hb": "חציך",
                    "gr": "βολίδες σου"
                },
                "7": {
                    "hb": "יהלכו",
                    "gr": "πορεύσονται"
                },
                "8": {
                    "hb": "לנגה",
                    "gr": "εἰς φέγγος"
                },
                "9": {
                    "hb": "ברק",
                    "gr": "ἀστραπῆς"
                },
                "10": {
                    "hb": "חניתך",
                    "gr": "ὅπλων σου"
                }
            },
            "12": {
                "1": {
                    "hb": "בזעם",
                    "gr": "ἐν ἀπειλῇ"
                },
                "2": {
                    "hb": "תצעד =תצער .dr",
                    "gr": "ὀλιγώσεις"
                },
                "3": {
                    "hb": "ארץ",
                    "gr": "γῆν"
                },
                "4": {
                    "hb": "באף",
                    "gr": "καὶ ἐν θυμῷ"
                },
                "5": {
                    "hb": "תדושׁ",
                    "gr": "κατάξεις"
                },
                "6": {
                    "hb": "גוים",
                    "gr": "ἔθνη"
                }
            },
            "13": {
                "1": {
                    "hb": "יצאת",
                    "gr": "ἐξῆλθες"
                },
                "2": {
                    "hb": "לישׁע",
                    "gr": "εἰς σωτηρίαν"
                },
                "3": {
                    "hb": "עמך",
                    "gr": "λαοῦ σου"
                },
                "4": {
                    "hb": "לישׁע",
                    "gr": "τοῦ σῶσαι"
                },
                "5": {
                    "hb": "את משׁיחך =v",
                    "gr": "τοὺς χριστούς σου"
                },
                "6": {
                    "hb": "מחצת",
                    "gr": "ἔβαλες"
                },
                "7": {
                    "hb": "{...}",
                    "gr": "εἰς"
                },
                "8": {
                    "hb": "ראשׁ",
                    "gr": "{..pεἰσ} κεφαλὰς"
                },
                "9": {
                    "hb": "מבית ^ =רשׁע",
                    "gr": "ἀνόμων"
                },
                "10": {
                    "hb": "^ רשׁע =מבית =מות",
                    "gr": "θάνατον"
                },
                "11": {
                    "hb": "ערות =@",
                    "gr": "ἐξήγειρας"
                },
                "12": {
                    "hb": "יסוד",
                    "gr": "δεσμοὺς"
                },
                "13": {
                    "hb": "עד",
                    "gr": "ἕως"
                },
                "14": {
                    "hb": "צואר",
                    "gr": "τραχήλου"
                },
                "15": {
                    "hb": "סלה",
                    "gr": "διάψαλμα"
                }
            },
            "14": {
                "1": {
                    "hb": "נקבת",
                    "gr": "διέκοψας"
                },
                "2": {
                    "hb": "במטיו",
                    "gr": "ἐν ἐκστάσει {cἐκτάσει}"
                },
                "3": {
                    "hb": "ראשׁ",
                    "gr": "κεφαλὰς"
                },
                "4": {
                    "hb": "*פרזו **פרזיו",
                    "gr": "δυναστῶν"
                },
                "5": {
                    "hb": "יסערו",
                    "gr": "σεισθήσονται"
                },
                "6": {
                    "hb": "--+",
                    "gr": "ἐν αὐτῇ"
                },
                "7": {
                    "hb": "להפיצני =@?פצח",
                    "gr": "διανοίξουσιν"
                },
                "8": {
                    "hb": "עליצתם =?מצלתמ,?@אלץ",
                    "gr": "χαλινοὺς αὐτῶν <za14.20>"
                },
                "9": {
                    "hb": "כמו",
                    "gr": "ὡς"
                },
                "10": {
                    "hb": "לאכל",
                    "gr": "ἔσθων"
                },
                "11": {
                    "hb": "עני",
                    "gr": "πτωχὸς"
                },
                "12": {
                    "hb": "במסתר",
                    "gr": "λάθρᾳ"
                }
            },
            "15": {
                "1": {
                    "hb": "דרכת",
                    "gr": "καὶ ἐπεβίβασας"
                },
                "2": {
                    "hb": "בים",
                    "gr": "εἰς θάλασσαν"
                },
                "3": {
                    "hb": "סוסיך",
                    "gr": "τοὺς ἵππους σου"
                },
                "4": {
                    "hb": "חמר =v",
                    "gr": "ταράσσοντας"
                },
                "5": {
                    "hb": "מים",
                    "gr": "ὕδωρ"
                },
                "6": {
                    "hb": "רבים",
                    "gr": "πολύ"
                }
            },
            "16": {
                "1": {
                    "hb": "שׁמעתי",
                    "gr": "ἐφυλαξάμην"
                },
                "2": {
                    "hb": "ותרגז",
                    "gr": "καὶ ἐπτοήθη"
                },
                "3": {
                    "hb": "בטני",
                    "gr": "ἡ κοιλία μου"
                },
                "4": {
                    "hb": "לקול",
                    "gr": "ἀπὸ φωνῆς"
                },
                "5": {
                    "hb": "צללו =@צלהa",
                    "gr": "προσευχῆς"
                },
                "6": {
                    "hb": "שׂפתי",
                    "gr": "χειλέων μου"
                },
                "7": {
                    "hb": "יבוא",
                    "gr": "καὶ εἰσῆλθεν"
                },
                "8": {
                    "hb": "רקב",
                    "gr": "τρόμος"
                },
                "9": {
                    "hb": "בעצמי",
                    "gr": "εἰς τὰ ὀστᾶ μου"
                },
                "10": {
                    "hb": "ותחתי",
                    "gr": "καὶ ὑποκάτωθέν μου"
                },
                "11": {
                    "hb": "ארגז =%vap",
                    "gr": "ἐταράχθη"
                },
                "12": {
                    "hb": "אשׁר =?אשׁור",
                    "gr": "ἡ ἕξις μου"
                },
                "13": {
                    "hb": "אנוח",
                    "gr": "ἀναπαύσομαι"
                },
                "14": {
                    "hb": "ליום",
                    "gr": "ἐν ἡμέρᾳ"
                },
                "15": {
                    "hb": "צרה",
                    "gr": "θλίψεως"
                },
                "16": {
                    "hb": "לעלות",
                    "gr": "τοῦ ἀναβῆναι"
                },
                "17": {
                    "hb": "לעם",
                    "gr": "εἰς λαὸν"
                },
                "18": {
                    "hb": "יגודנו =@גור",
                    "gr": "παροικίας μου"
                }
            },
            "17": {
                "1": {
                    "hb": "כי",
                    "gr": "διότι"
                },
                "2": {
                    "hb": "תאנה",
                    "gr": "συκῆ"
                },
                "3": {
                    "hb": "לא",
                    "gr": "οὐ"
                },
                "4": {
                    "hb": "תפרח =תפרה .xh",
                    "gr": "καρποφορήσει"
                },
                "5": {
                    "hb": "ואין",
                    "gr": "καὶ οὐκ ἔσται"
                },
                "6": {
                    "hb": "יבול",
                    "gr": "γενήματα"
                },
                "7": {
                    "hb": "בגפנים",
                    "gr": "ἐν ταῖς ἀμπέλοις"
                },
                "8": {
                    "hb": "כחשׁ",
                    "gr": "ψεύσεται"
                },
                "9": {
                    "hb": "מעשׂה",
                    "gr": "ἔργον"
                },
                "10": {
                    "hb": "זית",
                    "gr": "ἐλαίας"
                },
                "11": {
                    "hb": "ושׁדמות",
                    "gr": "καὶ τὰ πεδία"
                },
                "12": {
                    "hb": "לא",
                    "gr": "οὐ"
                },
                "13": {
                    "hb": "עשׂה",
                    "gr": "ποιήσει"
                },
                "14": {
                    "hb": "אכל",
                    "gr": "βρῶσιν"
                },
                "15": {
                    "hb": "גזר",
                    "gr": "ἐξέλιπον"
                },
                "16": {
                    "hb": "ממכלה =ממאכלה .אט",
                    "gr": "ἀπὸ βρώσεως"
                },
                "17": {
                    "hb": "צאן",
                    "gr": "πρόβατα"
                },
                "18": {
                    "hb": "ואין",
                    "gr": "καὶ οὐχ ὑπάρχουσιν"
                },
                "19": {
                    "hb": "בקר",
                    "gr": "βόες"
                },
                "20": {
                    "hb": "ברפתים",
                    "gr": "ἐπὶ φάτναις"
                }
            },
            "18": {
                "1": {
                    "hb": "ואני",
                    "gr": "ἐγὼ ^ δὲ"
                },
                "2": {
                    "hb": "ביהוה",
                    "gr": "ἐν τῷ κυρίῳ"
                },
                "3": {
                    "hb": "אעלוזה",
                    "gr": "ἀγαλλιάσομαι"
                },
                "4": {
                    "hb": "אגילה",
                    "gr": "χαρήσομαι"
                },
                "5": {
                    "hb": "באלהי",
                    "gr": "ἐπὶ τῷ θεῷ"
                },
                "6": {
                    "hb": "ישׁעי",
                    "gr": "τῷ σωτῆρί μου"
                }
            },
            "19": {
                "1": {
                    "hb": "יהוה",
                    "gr": "κύριος"
                },
                "2": {
                    "hb": "אדני",
                    "gr": "ὁ θεὸς"
                },
                "3": {
                    "hb": "חילי",
                    "gr": "δύναμίς μου"
                },
                "4": {
                    "hb": "וישׂם",
                    "gr": "καὶ τάξει"
                },
                "5": {
                    "hb": "רגלי",
                    "gr": "τοὺς πόδας μου"
                },
                "6": {
                    "hb": "כאילות =@כלה",
                    "gr": "εἰς συντέλειαν"
                },
                "7": {
                    "hb": "ועל",
                    "gr": "ἐπὶ"
                },
                "8": {
                    "hb": "במותי",
                    "gr": "τὰ ὑψηλὰ"
                },
                "9": {
                    "hb": "ידרכני",
                    "gr": "ἐπιβιβᾷ με"
                },
                "10": {
                    "hb": "למנצח",
                    "gr": "τοῦ νικῆσαι"
                },
                "11": {
                    "hb": "בנגינותי",
                    "gr": "ἐν τῇ ᾠδῇ αὐτοῦ"
                }
            }
        }
    }
}